qrllearner/__init__.py
qrllearner-0.2.dist-info/LICENSE.txt
qrllearner-0.2.dist-info/METADATA
qrllearner-0.2.dist-info/WHEEL
qrllearner-0.2.dist-info/top_level.txt
qrllearner-0.2.dist-info/RECORD
