Metadata-Version: 2.1
Name: qrllearner
Version: 0.2
Summary: This is a basic quantum reinfrocement learning agent based on Grove algorithm
Author: Zhanzhi Jiang
Author-email: hnzjzz@gmail.com
Classifier: Programming Language :: Python :: 3
Classifier: License :: OSI Approved :: MIT License
Classifier: Operating System :: OS Independent
License-File: LICENSE.txt
